{
	"PERSONA": [
		{
			"id": "241",
			"clave": "123",
			"direccion": "calle 26 norte caso 950",
			" mail": "Juan@email.com",
			"genero": "MASCULINO",
			"nombre": "Juan Paez",
			"id_ciudad": "52"
		},
		{
			"id": "123",
			"clave": "123",
			"direccion": "calle 26 norte caso 950",
			" mail": "carolina@email.com",
			"genero": "FEMENINO",
			"nombre": "Carolina Cruz",
			"id_ciudad": "52"
		},
		{
			"id": "451",
			"clave": "123",
			"direccion": "calle 26 norte caso 950",
			" mail": "diego@email.com",
			"genero": "MASCULINO",
			"nombre": "Diego Silva",
			"id_ciudad": "52"
		},
		{
			"id": "341",
			"clave": "123",
			"direccion": "calle 26 norte caso 950",
			" mail": "maria@email.com",
			"genero": "FEMENINO",
			"nombre": "Maria Castro",
			"id_ciudad": "52"
		},
		{
			"id": "989",
			"clave": "123",
			"direccion": "calle 26 norte caso 950",
			" mail": "sindy@email.com",
			"genero": "FEMENINO",
			"nombre": "Sindy Cuatin",
			"id_ciudad": "52"
		}
	]
}